README.rst
setup.py
src/cuisine.py
src/cuisine.egg-info/PKG-INFO
src/cuisine.egg-info/SOURCES.txt
src/cuisine.egg-info/dependency_links.txt
src/cuisine.egg-info/requires.txt
src/cuisine.egg-info/top_level.txt